pyraminxolver/__init__.py
pyraminxolver/cli.py
pyraminxolver/command_line.py
pyraminxolver/config.py
pyraminxolver/pyraminx.py
pyraminxolver/pyraminxolver.py
pyraminxolver/setup.py
PyraminXolver-1.0.1.dist-info/LICENSE
PyraminXolver-1.0.1.dist-info/METADATA
PyraminXolver-1.0.1.dist-info/WHEEL
PyraminXolver-1.0.1.dist-info/entry_points.txt
PyraminXolver-1.0.1.dist-info/top_level.txt
PyraminXolver-1.0.1.dist-info/RECORD
