Metadata-Version: 2.1
Name: PyraminXolver
Version: 1.0.1
Summary: This runs pyraminxolver Command Line
Home-page: https://github.com/Odder/PyraminXolver
Author: Oscar Roth Andersen
Author-email: oscarrothandersen@gmail.com
License: MIT
Download-URL: https://github.com/Odder/PyraminXolver/archive/v1.0.1.tar.gz
Platform: UNKNOWN
Requires-Python: >=3.7
